DependMLMoi/__init__.py
DependMLMoi/active_repo.py
DependMLMoi/arg_parser.py
DependMLMoi/constants.py
DependMLMoi/create_issues_from_todo.py
DependMLMoi/depend_ml.py
DependMLMoi/dependencies.py
DependMLMoi/main.py
scripts/__init__.py
scripts/main.py
dependMLOps-0.0.1.dist-info/LICENSE.txt
dependMLOps-0.0.1.dist-info/METADATA
dependMLOps-0.0.1.dist-info/WHEEL
dependMLOps-0.0.1.dist-info/entry_points.txt
dependMLOps-0.0.1.dist-info/top_level.txt
dependMLOps-0.0.1.dist-info/RECORD
