Metadata-Version: 2.1
Name: dependMLOps
Version: 0.0.1
Summary: Manage MLOps Dependencies and More...
Author: Nullzero
Author-email: Aylex Nullzero <p4rlx-news@pm.me>
Classifier: Programming Language :: Python :: 3.10
Classifier: License :: OSI Approved :: MIT License
Classifier: Operating System :: OS Independent
Requires-Python: >=3.9
License-File: LICENSE.txt
Requires-Dist: aiohttp ==3.8.3
Requires-Dist: aiosignal ==1.3.1
Requires-Dist: async-timeout ==4.0.3
Requires-Dist: cachetools ==5.3.2
Requires-Dist: packaging ==23.2
Requires-Dist: Pillow ==10.1.0
Requires-Dist: pipdeptree ==2.13.0
Requires-Dist: pytest ==7.4.3
Requires-Dist: pytest-asyncio ==0.21.1
Requires-Dist: pytest-mock ==3.12.0
Requires-Dist: python-dotenv ==1.0.0
Requires-Dist: tomli ==2.0.1
Requires-Dist: Tree ==0.2.4
Provides-Extra: dev
Requires-Dist: check-manifest ; extra == 'dev'
Requires-Dist: build ; extra == 'dev'
Provides-Extra: test
Requires-Dist: pytest ; extra == 'test'
